README.rst
setup.py
turing_machine.py
turing_machine.egg-info/PKG-INFO
turing_machine.egg-info/SOURCES.txt
turing_machine.egg-info/dependency_links.txt
turing_machine.egg-info/not-zip-safe
turing_machine.egg-info/top_level.txt