Metadata-Version: 1.1
Name: turing-machine
Version: 1.0
Summary: Turing Machine as a Python Generator.
Home-page: https://github.com/dimazest/turing_machine
Author: Dmitrijs Milajevs
Author-email: dimazest@gmail.com
License: MIT
Platform: UNKNOWN
Classifier: Development Status :: 3 - Alpha
Classifier: Operating System :: OS Independent
Classifier: Programming Language :: Python
Classifier: Intended Audience :: Developers
Classifier: Intended Audience :: Education
